{"type": "Feature", "id": 12524524, "geometry": {"type": "Point", "coordinates": [-76.97905, -0.46532]}, "properties": {"woe:id": 12524524, "woe:parent_id": 420033, "woe:name": "Coca Airport", "woe:placetype": 14, "woe:placetype_name": "Airport", "woe:lang": "ENG", "iso:country": "EC", "meta:provider": ["geoplanet:7.3.1", "geoplanet:7.3.2", "geoplanet:7.4.0", "geoplanet:7.4.1", "geoplanet:7.5.1", "geoplanet:7.5.2", "geoplanet:7.6.0", "geoplanet:7.8.1", "geoplanet:7.9.0", "geoplanet:7.10.0", "geoplanet:8.0.0", "woeplanet:8.0.0"], "meta:indexed": "2020-08-20T20:52:03.451419", "woe:alias_ENG_V": ["OCC Airport", "OCC"], "meta:updated": "2020-10-14T11:36:37.907127", "woe:hierarchy": {"continent": 24865673, "country": 23424801, "town": 0, "planet": 1, "county": 26809525, "suburb": 0, "state": 20070099, "region": 0, "localadmin": 26810319}, "woe:timezone_id": 28350762, "woe:hash": "6rcm273964h4", "woe:centroid": [-76.97905, -0.46532], "geom:latitude": -0.46532, "geom:longitude": -76.97905, "geom:hash": "6rcm273964h4", "woe:latitude": -0.46532, "geom:centroid": [-76.97905, -0.46532], "woe:longitude": -76.97905, "woe:repo": "woeplanet-airport-ec", "geom:area": 0.0, "woe:scale": 19}}